pytwinkly/__init__.py
pytwinkly/twinkly.py
pytwinkly-0.1.6.dist-info/LICENSE
pytwinkly-0.1.6.dist-info/METADATA
pytwinkly-0.1.6.dist-info/WHEEL
pytwinkly-0.1.6.dist-info/top_level.txt
pytwinkly-0.1.6.dist-info/RECORD
