Metadata-Version: 2.1
Name: pytwinkly
Version: 0.1.6
Summary: A package for integrating with twinkly lights
Home-page: https://github.com/scottjones4k/pytwinkly
Author: Scott Jones
Author-email: scott.jones4k@gmail.com
License: UNKNOWN
Platform: UNKNOWN
Classifier: Programming Language :: Python :: 3
Classifier: License :: OSI Approved :: MIT License
Classifier: Operating System :: OS Independent
Requires-Dist: asyncio
Requires-Dist: aiohttp
